renops/__init__.py
renops/config.py
renops/datafetcher.py
renops/geolocation.py
renops/geoshifter.py
renops/main.py
renops/scheduler.py
renops/utils.py
renops_scheduler-1.1.3.dist-info/METADATA
renops_scheduler-1.1.3.dist-info/WHEEL
renops_scheduler-1.1.3.dist-info/entry_points.txt
renops_scheduler-1.1.3.dist-info/licenses/LICENSE
renops_scheduler-1.1.3.dist-info/RECORD
