Metadata-Version: 2.3
Name: renops-scheduler
Version: 1.1.3
Summary: Scheduler shifts given scripts to time when most renewables available
Author-email: Jakob Jenko <jakob.jenko@xlab.si>
License-File: LICENSE
Classifier: License :: OSI Approved :: MIT License
Classifier: Operating System :: OS Independent
Classifier: Programming Language :: Python :: 3
Requires-Python: >=3.7
Requires-Dist: certifi>=2023.7.22
Requires-Dist: charset-normalizer==3.1.0
Requires-Dist: idna>=3.7
Requires-Dist: loguru
Requires-Dist: numpy==1.25.0
Requires-Dist: pandas==2.0.3
Requires-Dist: python-dateutil==2.8.2
Requires-Dist: pytz==2023.3
Requires-Dist: requests==2.32.2
Requires-Dist: six==1.16.0
Requires-Dist: tzdata==2023.3
Requires-Dist: urllib3>=2.0.7
